py.typed
sys_vars.py
sys_vars-5.1.0.dist-info/LICENSE
sys_vars-5.1.0.dist-info/METADATA
sys_vars-5.1.0.dist-info/WHEEL
sys_vars-5.1.0.dist-info/RECORD
