Metadata-Version: 2.1
Name: sys-vars
Version: 5.1.0
Summary: Access system variables in your code as native Python data types.
Home-page: https://github.com/le717/sys-vars
License: MIT
Author: Caleb
Author-email: le717@users.noreply.github.com
Requires-Python: >=3.8,<4.0
Classifier: License :: OSI Approved :: MIT License
Classifier: Programming Language :: Python :: 3
Classifier: Programming Language :: Python :: 3.8
Classifier: Programming Language :: Python :: 3.9
Classifier: Programming Language :: Python :: 3.10
Classifier: Programming Language :: Python :: 3.11
Classifier: Programming Language :: Python :: 3.12
Classifier: Typing :: Typed
Provides-Extra: dotenv
Requires-Dist: python-dotenv (>=1.0.1,<2.0.0) ; extra == "dotenv"
Project-URL: Repository, https://github.com/le717/sys-vars
